geckolib/__init__.py
geckolib/__main__.py
geckolib/_version.py
geckolib/async_locator.py
geckolib/async_spa.py
geckolib/async_spa_descriptor.py
geckolib/async_spa_manager.py
geckolib/async_taskman.py
geckolib/async_tasks.py
geckolib/config.py
geckolib/const.py
geckolib/spa_events.py
geckolib/spa_state.py
geckolib/automation/__init__.py
geckolib/automation/async_facade.py
geckolib/automation/bainultra.py
geckolib/automation/base.py
geckolib/automation/blower.py
geckolib/automation/bubblegen.py
geckolib/automation/button.py
geckolib/automation/heater.py
geckolib/automation/heatpump.py
geckolib/automation/ingrid.py
geckolib/automation/inmix.py
geckolib/automation/keypad.py
geckolib/automation/keypad_backlight.py
geckolib/automation/light.py
geckolib/automation/lockmode.py
geckolib/automation/mrsteam.py
geckolib/automation/number.py
geckolib/automation/power.py
geckolib/automation/pump.py
geckolib/automation/reminders.py
geckolib/automation/select.py
geckolib/automation/sensors.py
geckolib/automation/switch.py
geckolib/automation/watercare.py
geckolib/automation/waterfall.py
geckolib/driver/__init__.py
geckolib/driver/accessor.py
geckolib/driver/async_peekablequeue.py
geckolib/driver/async_spastruct.py
geckolib/driver/async_udp_protocol.py
geckolib/driver/observable.py
geckolib/driver/udp_protocol_handler.py
geckolib/driver/packs/__init__.py
geckolib/driver/packs/inclear-32k-cfg-2.py
geckolib/driver/packs/inclear-32k-log-3.py
geckolib/driver/packs/inclear-32k.py
geckolib/driver/packs/ink600-64k.py
geckolib/driver/packs/inmix-cfg-1.py
geckolib/driver/packs/inmix-cfg-2.py
geckolib/driver/packs/inmix-cfg-3.py
geckolib/driver/packs/inmix-cfg-4.py
geckolib/driver/packs/inmix-cfg-5.py
geckolib/driver/packs/inmix-log-1.py
geckolib/driver/packs/inmix-log-2.py
geckolib/driver/packs/inmix.py
geckolib/driver/packs/inmixextended-cfg-3.py
geckolib/driver/packs/inmixextended-cfg-4.py
geckolib/driver/packs/inmixextended-cfg-5.py
geckolib/driver/packs/inmixextended-log-1.py
geckolib-1.0.14.dist-info/LICENSE
geckolib-1.0.14.dist-info/METADATA
geckolib-1.0.14.dist-info/WHEEL
geckolib-1.0.14.dist-info/top_level.txt
geckolib-1.0.14.dist-info/RECORD
