Metadata-Version: 2.2
Name: geckolib
Version: 1.0.14
Summary: An async library to interface with Gecko Alliance products using in.touch2
Home-page: https://github.com/gazoodle/geckolib
Author: Gazoodle
License: GPLv3
Keywords: Gecko Alliance,in.touch2,library,Home Automation
Classifier: Development Status :: 4 - Beta
Classifier: Programming Language :: Python :: 3.13
Classifier: Intended Audience :: Developers
Classifier: Topic :: Software Development :: Libraries
Classifier: License :: OSI Approved :: GNU General Public License v3 (GPLv3)
Classifier: Operating System :: OS Independent
Requires-Python: >=3.13
License-File: LICENSE
